b_cf_outputs/__init__.py
b_cf_outputs/cf_outputs.py
b_cf_outputs/cf_stacks.py
b_cf_outputs_test/mocks/__init__.py
b_cf_outputs_test/mocks/boto_session_mock.py
b_cf_outputs_test/mocks/cloud_formation_mock.py
b_cf_outputs-1.0.0.dist-info/LICENSE
b_cf_outputs-1.0.0.dist-info/METADATA
b_cf_outputs-1.0.0.dist-info/WHEEL
b_cf_outputs-1.0.0.dist-info/top_level.txt
b_cf_outputs-1.0.0.dist-info/RECORD
