Metadata-Version: 2.1
Name: b-cf-outputs
Version: 1.0.0
Summary: Package that helps to gather AWS CloudFormation outputs.
Home-page: https://github.com/biomapas/B.CfOutputs.git
Author: Laimonas Sutkus
Author-email: laimonas.sutkus@biomapas.com
License: Apache License 2.0
Keywords: AWS CloudFormation Output
Platform: UNKNOWN
Classifier: Programming Language :: Python :: 3
Classifier: Operating System :: OS Independent
License-File: LICENSE
Requires-Dist: boto3 (<2.0.0,>=1.14.0)
Requires-Dist: pytest (<7.0.0,>=6.0.2)
Requires-Dist: pytest-cov (<3.0.0,>=2.10.1)
